{
    "鼠标指针样式cursor的设置":{
        "auto":"默认的鼠标小箭头",
        "pointer":"显示为手型",
        "wait":"加载中旋转的图标",
        "alias":"别名，带有一个翻转的小箭头",
        "all-scroll":"四个方向的箭头",
        "move":"四个方向的箭头",
        "cell":"表格的指针",
        "col-resize":"更改列宽度的标志",
        "copy":"右上角有个加号",
        "crosshair":"十字",
        "e-resize":"水平方向箭头",
        "ew-resize":"水平方向箭头",
        "grab":"要抓取的小手",
        "grabbing":"抓取中的小手",
        "help":"带有一个问号",
        "no-drop":"禁止拖动按钮",
        "n-resize":"南北指向的箭头",
        "nesw-resize":"北东南西四个方向的箭头",
        "text":"编辑光标",
        "row-resize":"更改行宽度的标志",
        "progress":"带有旋转小圆圈的鼠标",
        "vertical-text":"垂直编辑文本",
        "zoom-in":"放大",
        "zoom-out":"缩小",
        "unset":"重置",
        "default":"默认",
        "none":"不显示任何光标"
    },
    "列表样式list-style-type的可选项":{
        "circle":"",
        "disc":"",
        "decimal":"阿拉伯数字",
        "decimal-leading-zero":"带有前导零的阿拉伯数字",
        "lower-alpha":"小写英文字母",
        "simp-chinese-informal":"（小写）非正式的简体中文汉字",
        "simp-chinese-formal":"（大写）正式的简体中文汉字",
        "trad-chinese-informal":"（小写）非正式的传统中文汉字",
        "trad-chinese-formal":"（大写）正式的传统中文汉字",
        "square":"实心小方块"
    },
    "伪选择器":{
        ":nth-child()":"匹配第几个元素",
        ":nth--of-type()":"匹配指定元素类型的第几个元素",
        ":target":"匹配具有指定hash值的元素",
        ":empty":"匹配没有任何内容的标签",
        ":only-child":"匹配属于其父元素的唯一一个元素",
        ":not()":"否定伪类，排除符合条件的元素",
        ":focus":"元素被聚焦时",
        ":blur":"元素失焦时",
        ":first-letter":"第一个字母",
        ":first-line":"第一行",
        ":before":"在元素首添加一个新元素",
        ":after":"在元素尾添加一个新元素",
        "::selection":"设置鼠标选中文字时的样式",
    },
    "防止margin上溢出的解决方法":[
        "给父元素设置border",
        "添加一个before伪元素，模型为table",
        "设置父元素溢出隐藏 overflow:hidden"
    ],
    "防止父容器高度塌陷的解决方法":[
        "给父容器设置高度",
        "添加一个after伪元素，清除浮动",
        "给父容器设置浮动，即脱离文档流",
        "设置父容器溢出隐藏"
    ]
}